odoo/addons/l10n_es_pos/README.rst
odoo/addons/l10n_es_pos/__init__.py
odoo/addons/l10n_es_pos/__manifest__.py
odoo/addons/l10n_es_pos/hooks.py
odoo/addons/l10n_es_pos/i18n/ca.po
odoo/addons/l10n_es_pos/i18n/ca_ES.po
odoo/addons/l10n_es_pos/i18n/es.po
odoo/addons/l10n_es_pos/i18n/eu.po
odoo/addons/l10n_es_pos/i18n/eu_ES.po
odoo/addons/l10n_es_pos/i18n/l10n_es_pos.pot
odoo/addons/l10n_es_pos/models/__init__.py
odoo/addons/l10n_es_pos/models/ir_sequence.py
odoo/addons/l10n_es_pos/models/pos_config.py
odoo/addons/l10n_es_pos/models/pos_order.py
odoo/addons/l10n_es_pos/static/description/icon.png
odoo/addons/l10n_es_pos/static/src/js/models.js
odoo/addons/l10n_es_pos/static/src/js/screens.js
odoo/addons/l10n_es_pos/static/src/xml/pos.xml
odoo/addons/l10n_es_pos/views/pos_templates.xml
odoo/addons/l10n_es_pos/views/pos_views.xml
odoo12_addon_l10n_es_pos-12.0.2.0.0.99.dev10.dist-info/METADATA
odoo12_addon_l10n_es_pos-12.0.2.0.0.99.dev10.dist-info/WHEEL
odoo12_addon_l10n_es_pos-12.0.2.0.0.99.dev10.dist-info/top_level.txt
odoo12_addon_l10n_es_pos-12.0.2.0.0.99.dev10.dist-info/RECORD
