Metadata-Version: 2.1
Name: odoo12-addon-l10n-es-pos
Version: 12.0.2.0.0.99.dev10
Summary: Punto de venta adaptado a la legislación española
Home-page: https://github.com/OCA/l10n-spain
Author: Tecnativa, Aselcis Consulting, Acysos S.L., Odoo Community Association (OCA)
Author-email: support@odoo-community.org
License: AGPL-3
Platform: UNKNOWN
Classifier: Programming Language :: Python
Classifier: Framework :: Odoo
Classifier: Framework :: Odoo :: 12.0
Classifier: License :: OSI Approved :: GNU Affero General Public License v3
Requires-Python: >=3.5
Requires-Dist: odoo <12.1dev,>=12.0a
